{
  "id": "tongueLashing",
  "name": "Tongue Lashing",
  "series": "megamix",
  "priority": 1,
  "objects": [
    {
      "type": "cue",
      "id": "*/yellowBugAppear",
      "name": "[#FFE600]yellow bug[] - appear",
      "deprecatedIDs": [
        "tongueLashing/three"
      ],
      "subtext": "",
      "duration": 0.5
    },
    {
      "type": "cue",
      "id": "*/redBugAppear",
      "name": "[#FF1A01]red bug[] - appear",
      "deprecatedIDs": [
        "tongueLashing/red"
      ],
      "subtext": "",
      "duration": 0.5
    },
    {
      "type": "cue",
      "id": "*/whip",
      "name": "whip lash",
      "deprecatedIDs": [],
      "subtext": "",
      "duration": 0.5
    },
    {
      "type": "cue",
      "id": "*/gulpLong",
      "name": "gulp - 1",
      "deprecatedIDs": [
        "tongueLashing/gulp4"
      ],
      "subtext": "",
      "duration": 0.5
    },
    {
      "type": "cue",
      "id": "*/gulp",
      "name": "gulp - 2",
      "deprecatedIDs": [],
      "subtext": "",
      "duration": 0.5
    },
    {
      "type": "cue",
      "id": "*/guyYes",
      "name": "guy - yes",
      "deprecatedIDs": [
        "tongueLashing/yes"
      ],
      "subtext": "",
      "duration": 0.5
    },
    {
      "type": "cue",
      "id": "*/guyLaugh",
      "name": "guy - laugh",
      "deprecatedIDs": [
        "tongueLashing/laughter"
      ],
      "subtext": "",
      "duration": 0.5
    },
    {
      "type": "cue",
      "id": "*/guyTeehee",
      "name": "guy - teehee",
      "deprecatedIDs": [
        "tongueLashing/teehee"
      ],
      "subtext": "",
      "duration": 0.5
    },
    {
      "type": "pattern",
      "id": "*_yellowBugLong",
      "name": "long [#FFE600]yellow bug[]",
      "deprecatedIDs": [
        "tongueLashing_yellowbuglong"
      ],
      "cues": [
        {
          "id": "*/yellowBugAppear",
          "beat": 0.0
        },
        {
          "id": "*/whip",
          "beat": 2.0
        },
        {
          "id": "*/gulpLong",
          "beat": 2.5
        },
        {
          "id": "*/gulp",
          "beat": 3.0
        }
      ],
      "subtext": ""
    },
    {
      "type": "pattern",
      "id": "*_yellowBugShort",
      "name": "short [#FFE600]yellow bug[]",
      "deprecatedIDs": [
        "tongueLashing_yellowbugshort"
      ],
      "cues": [
        {
          "id": "*/yellowBugAppear",
          "beat": 0.0
        },
        {
          "id": "*/whip",
          "beat": 2.0
        },
        {
          "id": "*/gulp",
          "beat": 2.5
        }
      ],
      "subtext": ""
    },
    {
      "type": "pattern",
      "id": "*_redBugLong",
      "name": "long [#FF1A01]red bug[]",
      "deprecatedIDs": [
        "tongueLashing_redbuglong"
      ],
      "cues": [
        {
          "id": "*/redBugAppear",
          "beat": 0.0
        },
        {
          "id": "*/whip",
          "beat": 3.0
        },
        {
          "id": "*/gulpLong",
          "beat": 3.5
        },
        {
          "id": "*/gulp",
          "beat": 4.0
        }
      ],
      "subtext": ""
    },
    {
      "type": "pattern",
      "id": "*_redBugShort",
      "name": "short [#FF1A01]red bug[]",
      "deprecatedIDs": [
        "tongueLashing_redbugshort"
      ],
      "cues": [
        {
          "id": "*/redBugAppear",
          "beat": 0.0
        },
        {
          "id": "*/whip",
          "beat": 3.0
        },
        {
          "id": "*/gulp",
          "beat": 3.5
        }
      ],
      "subtext": ""
    },
    {
      "type": "pattern",
      "id": "*_redBugShortYes",
      "name": "short [#FF1A01]red bug[] - yes",
      "deprecatedIDs": [
        "tongueLashing_redbugshortyes"
      ],
      "cues": [
        {
          "id": "*/redBugAppear",
          "beat": 0.0
        },
        {
          "id": "*/whip",
          "beat": 3.0
        },
        {
          "id": "*/gulp",
          "beat": 3.5
        },
        {
          "id": "*/guyYes",
          "beat": 4.0
        }
      ],
      "subtext": ""
    },
    {
      "type": "pattern",
      "id": "*_redBugShortLaugh",
      "name": "short [#FF1A01]red bug[] - laugh",
      "deprecatedIDs": [
        "tongueLashing_redbugshortlaughing"
      ],
      "cues": [
        {
          "id": "*/redBugAppear",
          "beat": 0.0
        },
        {
          "id": "*/whip",
          "beat": 3.0
        },
        {
          "id": "*/gulp",
          "beat": 3.5
        },
        {
          "id": "*/guyLaugh",
          "beat": 4.0
        }
      ],
      "subtext": ""
    },
    {
      "type": "pattern",
      "id": "*_redBugShortTeehee",
      "name": "short [#FF1A01]red bug[] teehee",
      "deprecatedIDs": [
        "tongueLashing_redbugshortteehee"
      ],
      "cues": [
        {
          "id": "*/redBugAppear",
          "beat": 0.0
        },
        {
          "id": "*/whip",
          "beat": 3.0
        },
        {
          "id": "*/gulp",
          "beat": 3.5
        },
        {
          "id": "*/guyTeehee",
          "beat": 4.0
        }
      ],
      "subtext": ""
    }
  ]
}