{"series": "fever",
  "id": "donkDonkJa",
  "deprecatedIDs": [],
  "name": "Donk-Donk (Japanese)",
  "requiresVersion": "v3.0.0",
  "group": "Donk-Donk",
  "objects": [
    {
      "type": "cue",
      "id": "donkDonkJa/donk1",
      "deprecatedIDs": [
        "donkDonkJp/donk1"
      ],
      "name": "donk-donk - 1",
      "duration": 0.666666
    },
    {
      "type": "cue",
      "id": "donkDonkJa/donk2",
      "deprecatedIDs": [
        "donkDonkJp/donk2"
      ],
      "name": "donk-donk - 2",
      "duration": 0.666666
    },
    {
      "type": "cue",
      "id": "donkDonkJa/dwonk1",
      "deprecatedIDs": [
        "donkDonkJp/dwonk1"
      ],
      "name": "donk-dwonk - 1",
      "duration": 0.666666
    },
    {
      "type": "cue",
      "id": "donkDonkJa/dwonk2",
      "deprecatedIDs": [
        "donkDonkJp/dwonk2"
      ],
      "name": "donk-dwonk - 2",
      "duration": 0.666666
    },
    {
      "type": "cue",
      "id": "donkDonkJa/deetdeetduh1",
      "deprecatedIDs": [
        "donkDonkJp/deetdeetduh1"
      ],
      "name": "deet-deet-duh - 1",
      "duration": 0.666666
    },
    {
      "type": "cue",
      "id": "donkDonkJa/deetdeetduh2",
      "deprecatedIDs": [
        "donkDonkJp/deetdeetduh2"
      ],
      "name": "deet-deet-duh - 2",
      "duration": 0.666666
    },
    {
      "type": "cue",
      "id": "donkDonkJa/deetdeetduh3",
      "deprecatedIDs": [
        "donkDonkJp/deetdeetduh3"
      ],
      "name": "deet-deet-duh - 3",
      "duration": 0.666666
    },
    {
      "type": "cue",
      "id": "donkDonkJa/deetdeetdoot1",
      "deprecatedIDs": [
        "donkDonkJp/deetdeetdoot1"
      ],
      "name": "deet-deet-doot - 1",
      "duration": 0.666666
    },
    {
      "type": "cue",
      "id": "donkDonkJa/deetdeetdoot2",
      "deprecatedIDs": [
        "donkDonkJp/deetdeetdoot2"
      ],
      "name": "deet-deet-doot - 2",
      "duration": 0.666666
    },
    {
      "type": "cue",
      "id": "donkDonkJa/deetdeetdoot3",
      "deprecatedIDs": [
        "donkDonkJp/deetdeetdoot3"
      ],
      "name": "deet-deet-doot - 3",
      "duration": 0.666666
    },
    {
      "type": "cue",
      "id": "donkDonkJa/deetdeetdootNoBlast1",
      "deprecatedIDs": [],
      "name": "deet-deet-doot (no blast) - 1",
      "duration": 0.666666
    },
    {
      "type": "cue",
      "id": "donkDonkJa/deetdeetdootNoBlast2",
      "deprecatedIDs": [],
      "name": "deet-deet-doot (no blast) - 2",
      "duration": 0.666666
    },
    {
      "type": "cue",
      "id": "donkDonkJa/deetdeetdootNoBlast3",
      "deprecatedIDs": [],
      "name": "deet-deet-doot (no blast) - 3",
      "duration": 0.666666
    },
    {
      "type": "cue",
      "id": "donkDonkJa/blastoff",
      "deprecatedIDs": [
        "donkDonkJp/blastoff"
      ],
      "name": "blastoff",
      "duration": 1.0
    },
    {
      "type": "pattern",
      "id": "donkDonkJa_donkdonk",
      "deprecatedIDs": [
        "donkDonkJp_donkdonk"
      ],
      "name": "donk-donk",
      "cues": [
        {
          "id": "donkDonkJa/donk1",
          "beat": 0.0
        },
        {
          "id": "donkDonkJa/donk2",
          "beat": 0.666666
        }
      ]
    },
    {
      "type": "pattern",
      "id": "donkDonkJa_donkdwonk",
      "deprecatedIDs": [
        "donkDonkJp_donkdwonk"
      ],
      "name": "donk-dwonk",
      "cues": [
        {
          "id": "donkDonkJa/dwonk1",
          "beat": 0.0
        },
        {
          "id": "donkDonkJa/dwonk2",
          "beat": 0.666666
        }
      ]
    },
    {
      "type": "pattern",
      "id": "donkDonkJa_deetdeetduh",
      "deprecatedIDs": [
        "donkDonkJp_deetdeetduh"
      ],
      "name": "deet-deet-duh",
      "cues": [
        {
          "id": "donkDonkJa/deetdeetduh1",
          "beat": 0.0
        },
        {
          "id": "donkDonkJa/deetdeetduh2",
          "beat": 0.666666
        },
        {
          "id": "donkDonkJa/deetdeetduh3",
          "beat": 1.333333
        }
      ]
    },
    {
      "type": "pattern",
      "id": "donkDonkJa_deetdeetdoot",
      "deprecatedIDs": [
        "donkDonkJp_deetdeetdoot"
      ],
      "name": "deet-deet-doot",
      "cues": [
        {
          "id": "donkDonkJa/deetdeetdoot1",
          "beat": 0.0
        },
        {
          "id": "donkDonkJa/deetdeetdoot2",
          "beat": 0.666666
        },
        {
          "id": "donkDonkJa/deetdeetdoot3",
          "beat": 1.333333
        }
      ]
    },
    {
      "type": "pattern",
      "id": "donkDonkJa_deetdeetdootNoBlast",
      "deprecatedIDs": [],
      "name": "deet-deet-doot (no blast)",
      "cues": [
        {
          "id": "donkDonkJa/deetdeetdootNoBlast1",
          "beat": 0.0
        },
        {
          "id": "donkDonkJa/deetdeetdootNoBlast2",
          "beat": 0.666666
        },
        {
          "id": "donkDonkJa/deetdeetdootNoBlast3",
          "beat": 1.333333
        }
      ]
    },
    {
      "type": "pattern",
      "id": "donkDonkJa_toastsaot",
      "deprecatedIDs": [
        "donkDonkJp_toastsaot"
      ],
      "name": "DWONKAME!",
      "cues": [
        {
          "id": "donkDonkJa/dwonk2",
          "beat": 0.0
        },
        {
          "id": "donkDonkJa/dwonk2",
          "beat": 0.0,
          "track": 1
        },
        {
          "id": "donkDonkJa/dwonk2",
          "beat": 0.0,
          "track": 2
        },
        {
          "id": "donkDonkJa/dwonk2",
          "beat": 0.0,
          "track": 3
        },
        {
          "id": "donkDonkJa/dwonk2",
          "beat": 0.0,
          "track": 4
        }
      ]
    }
  ]
}