{"series": "side",
  "id": "samuraiSliceDS",
  "deprecatedIDs": [],
  "name": "Samurai Slice (DS)",
  "requiresVersion": "v3.0.0",
  "objects": [
    {
      "type": "cue",
      "id": "samuraiSliceDS/throw",
      "deprecatedIDs": [],
      "name": "throw",
      "duration": 1.0
    },
    {
      "type": "cue",
      "id": "samuraiSliceDS/faster1",
      "deprecatedIDs": [],
      "name": "fasterA",
      "duration": 1.0
    },
    {
      "type": "cue",
      "id": "samuraiSliceDS/faster2",
      "deprecatedIDs": [],
      "name": "fasterB",
      "duration": 1.0
    },
    {
      "type": "cue",
      "id": "samuraiSliceDS/faster3",
      "deprecatedIDs": [],
      "name": "fasterC",
      "duration": 1.0
    },
    {
      "type": "cue",
      "id": "samuraiSliceDS/see-sawA",
      "deprecatedIDs": [
        "samuraiSliceDS/see-saw"
      ],
      "name": "see-sawA",
      "duration": 1.0
    },
    {
      "type": "cue",
      "id": "samuraiSliceDS/see-sawB",
      "deprecatedIDs": [],
      "name": "see-sawB",
      "duration": 1.0
    },
    {
      "type": "cue",
      "id": "samuraiSliceDS/sliceA",
      "deprecatedIDs": [],
      "name": "sliceA",
      "duration": 1.0
    },
    {
      "type": "cue",
      "id": "samuraiSliceDS/sliceB",
      "deprecatedIDs": [],
      "name": "sliceB",
      "duration": 1.0
    },
    {
      "type": "cue",
      "id": "samuraiSliceDS/catch",
      "deprecatedIDs": [],
      "name": "catch",
      "duration": 1.0
    },
    {
      "type": "pattern",
      "id": "samuraiSliceDS_watermelon",
      "deprecatedIDs": [],
      "name": "watermelon",
      "cues": [
        {
          "id": "samuraiSliceDS/throw",
          "beat": 0.0
        },
        {
          "id": "samuraiSliceDS/see-sawB",
          "beat": 2.0
        },
        {
          "id": "samuraiSliceDS/sliceA",
          "beat": 4.0
        },
        {
          "id": "samuraiSliceDS/catch",
          "beat": 5.0
        }
      ]
    },
    {
      "type": "pattern",
      "id": "samuraiSliceDS_watermelonDouble",
      "deprecatedIDs": [],
      "name": "watermelon double",
      "cues": [
        {
          "id": "samuraiSliceDS/throw",
          "beat": 0.0,
          "track": 1
        },
        {
          "id": "samuraiSliceDS/throw",
          "beat": 1.0,
          "track": 1
        },
        {
          "id": "samuraiSliceDS/see-sawB",
          "beat": 2.0,
          "track": 1
        },
        {
          "id": "samuraiSliceDS/see-sawA",
          "beat": 3.0,
          "track": 1
        },
        {
          "id": "samuraiSliceDS/sliceA",
          "beat": 4.0,
          "track": 1
        },
        {
          "id": "samuraiSliceDS/catch",
          "beat": 5.0,
          "track": 1
        },
        {
          "id": "samuraiSliceDS/sliceA",
          "beat": 5.0
        },
        {
          "id": "samuraiSliceDS/catch",
          "beat": 6.0,
          "track": 1
        }
      ]
    },
    {
      "type": "pattern",
      "id": "samuraiSliceDS_fish",
      "deprecatedIDs": [],
      "name": "fish",
      "cues": [
        {
          "id": "samuraiSliceDS/throw",
          "beat": 0.0
        },
        {
          "id": "samuraiSliceDS/see-sawA",
          "beat": 2.0
        },
        {
          "id": "samuraiSliceDS/see-sawB",
          "beat": 4.0
        },
        {
          "id": "samuraiSliceDS/sliceA",
          "beat": 6.0
        },
        {
          "id": "samuraiSliceDS/catch",
          "beat": 7.0
        }
      ]
    },
    {
      "type": "pattern",
      "id": "samuraiSliceDS_fishDouble",
      "deprecatedIDs": [],
      "name": "fish double",
      "cues": [
        {
          "id": "samuraiSliceDS/throw",
          "beat": 0.0,
          "track": 1
        },
        {
          "id": "samuraiSliceDS/throw",
          "beat": 1.0,
          "track": 1
        },
        {
          "id": "samuraiSliceDS/see-sawA",
          "beat": 2.0,
          "track": 1
        },
        {
          "id": "samuraiSliceDS/see-sawB",
          "beat": 3.0,
          "track": 1
        },
        {
          "id": "samuraiSliceDS/see-sawA",
          "beat": 4.0,
          "track": 1
        },
        {
          "id": "samuraiSliceDS/see-sawB",
          "beat": 5.0,
          "track": 1
        },
        {
          "id": "samuraiSliceDS/sliceB",
          "beat": 6.0,
          "track": 1
        },
        {
          "id": "samuraiSliceDS/catch",
          "beat": 7.0,
          "track": 1
        },
        {
          "id": "samuraiSliceDS/sliceB",
          "beat": 7.0
        },
        {
          "id": "samuraiSliceDS/catch",
          "beat": 8.0,
          "track": 1
        }
      ]
    },
    {
      "type": "pattern",
      "id": "samuraiSliceDS_demon",
      "deprecatedIDs": [],
      "name": "demon",
      "cues": [
        {
          "id": "samuraiSliceDS/throw",
          "beat": 0.0
        },
        {
          "id": "samuraiSliceDS/see-sawA",
          "beat": 2.0
        },
        {
          "id": "samuraiSliceDS/sliceB",
          "beat": 6.0
        },
        {
          "id": "samuraiSliceDS/catch",
          "beat": 7.0
        }
      ]
    },
    {
      "type": "pattern",
      "id": "samuraiSliceDS_demonDouble",
      "deprecatedIDs": [],
      "name": "demon double",
      "cues": [
        {
          "id": "samuraiSliceDS/throw",
          "beat": 0.0,
          "track": 1
        },
        {
          "id": "samuraiSliceDS/throw",
          "beat": 1.0,
          "track": 1
        },
        {
          "id": "samuraiSliceDS/see-sawB",
          "beat": 2.0,
          "track": 1
        },
        {
          "id": "samuraiSliceDS/see-sawB",
          "beat": 3.0,
          "track": 1
        },
        {
          "id": "samuraiSliceDS/sliceB",
          "beat": 6.0,
          "track": 1
        },
        {
          "id": "samuraiSliceDS/catch",
          "beat": 7.0
        },
        {
          "id": "samuraiSliceDS/sliceA",
          "beat": 7.0,
          "track": 1
        },
        {
          "id": "samuraiSliceDS/catch",
          "beat": 8.0,
          "track": 1
        }
      ]
    }
  ]
}